bitget/__init__.py
bitget/bitget_api.py
bitget/client.py
bitget/mix/__init__.py
bitget/mix/account_api.py
bitget/mix/market_api.py
bitget/mix/order_api.py
bitget/spot/__init__.py
bitget/spot/account_api.py
bitget/spot/market_api.py
bitget/spot/order_api.py
bitget/spot/wallet_api.py
bitget/utils/__init__.py
bitget/utils/consts.py
bitget/utils/exceptions.py
bitget/utils/hash.py
bitget/utils/ws_hash.py
examples/__init__.py
examples/mix_example.py
examples/ws_example.py
bitget_connector-0.2.0.dist-info/LICENSE
bitget_connector-0.2.0.dist-info/METADATA
bitget_connector-0.2.0.dist-info/WHEEL
bitget_connector-0.2.0.dist-info/top_level.txt
bitget_connector-0.2.0.dist-info/RECORD
